shdw/__init__.py
shdw-0.0.15.dist-info/LICENSE
shdw-0.0.15.dist-info/METADATA
shdw-0.0.15.dist-info/WHEEL
shdw-0.0.15.dist-info/top_level.txt
shdw-0.0.15.dist-info/RECORD
