Metadata-Version: 2.1
Name: shdw
Version: 0.0.15
Summary: a package for random functions
Home-page: https://github.com/shibby360/shdwdb
Author: shibby360
Author-email: shibby360 <shivank.chhaya@gmail.com>
License: MIT
Project-URL: Homepage, https://github.com/shibby360/shdw-pckg
Requires-Python: >=3.8.18
License-File: LICENSE
